<?xml version="1.0" encoding="UTF-8"?>
<objects serializationModel="Studio.02.02.00">
	<object class="AudioFile" id="{32307fd6-7902-4ed6-bc56-61cd3fd3632a}">
		<property name="assetPath">
			<value>Drawer_Close_1.wav</value>
		</property>
		<property name="frequencyInKHz">
			<value>96</value>
		</property>
		<property name="channelCount">
			<value>2</value>
		</property>
		<property name="length">
			<value>1.1499999999999999</value>
		</property>
		<relationship name="masterAssetFolder">
			<destination>{e7e135d7-3505-4c53-9612-af0653256f2b}</destination>
		</relationship>
	</object>
</objects>
